waitress_fastlisten.py
waitress_fastlisten-1.0.0rc1.dist-info/LICENSE.txt
waitress_fastlisten-1.0.0rc1.dist-info/METADATA
waitress_fastlisten-1.0.0rc1.dist-info/WHEEL
waitress_fastlisten-1.0.0rc1.dist-info/entry_points.txt
waitress_fastlisten-1.0.0rc1.dist-info/top_level.txt
waitress_fastlisten-1.0.0rc1.dist-info/RECORD
