Metadata-Version: 2.1
Name: waitress-fastlisten
Version: 1.0.0rc1
Summary: Fast listen on port as a wrapper for waitress WSGI server.
Home-page: https://github.com/plone/waitress_fastlisten
Author: The Plone Community and Jens Klein
Author-email: tech@kleinundpartner.at
License: ZPL 2.1
Keywords: waitress wgi
Platform: UNKNOWN
Classifier: Development Status :: 5 - Production/Stable
Classifier: Intended Audience :: System Administrators
Classifier: Topic :: Internet :: WWW/HTTP :: WSGI
Classifier: License :: OSI Approved :: Zope Public License
Classifier: Operating System :: OS Independent
Classifier: Programming Language :: Python
Classifier: Programming Language :: Python :: 3.7
Classifier: Programming Language :: Python :: 3.8
Classifier: Programming Language :: Python :: 3.9
Requires-Dist: setuptools
Requires-Dist: waitress
